ali/__init__.py
ali/version.py
ZhiFuBaoSDK-0.0.0.dist-info/METADATA
ZhiFuBaoSDK-0.0.0.dist-info/WHEEL
ZhiFuBaoSDK-0.0.0.dist-info/top_level.txt
ZhiFuBaoSDK-0.0.0.dist-info/RECORD
