Metadata-Version: 2.1
Name: ZhiFuBaoSDK
Version: 0.0.0
Summary: AliPaySDK是基于支付宝开发的sdk
Home-page: https://gitee.com/navysummer/AliPaySDK
Author: navysummer
Author-email: navysummer@yeah.net
License: UNKNOWN
Platform: python
Classifier: Programming Language :: Python :: 3
Classifier: Programming Language :: Python :: 2
Classifier: Operating System :: OS Independent
Requires-Python: >=2.7
Requires-Dist: requests (~=2.27.1)
Requires-Dist: qrcode (~=7.3.1)
Requires-Dist: Pillow (~=9.0.1)
Requires-Dist: cryptography (~=36.0.2)
